CONTRIBUTING.rst
HISTORY.rst
LICENSE
MANIFEST.in
README.rst
setup.cfg
setup.py
trackingmore.py
kupfer_plugin_trackingmore.egg-info/PKG-INFO
kupfer_plugin_trackingmore.egg-info/SOURCES.txt
kupfer_plugin_trackingmore.egg-info/dependency_links.txt
kupfer_plugin_trackingmore.egg-info/not-zip-safe
kupfer_plugin_trackingmore.egg-info/top_level.txt