Metadata-Version: 1.1
Name: kupfer-plugin-trackingmore
Version: 0.1.0
Summary: Use trackingmore.com for package tracking
Home-page: https://github.com/hugosenari/trackingmore
Author: Hugo Sena Ribeiro
Author-email: hugosenari@gmail.com
License: MIT license
Keywords: kupfer trackingmore
Platform: UNKNOWN
Classifier: Development Status :: 2 - Pre-Alpha
Classifier: Intended Audience :: Developers
Classifier: License :: OSI Approved :: MIT License
Classifier: Natural Language :: English
Classifier: Programming Language :: Python :: 2
Classifier: Programming Language :: Python :: 2.7
Classifier: Programming Language :: Python :: 3
Classifier: Programming Language :: Python :: 3.3
Classifier: Programming Language :: Python :: 3.4
Classifier: Programming Language :: Python :: 3.5
